youtubevideosorter/cli.py
youtubevideosorter-1.2.dist-info/licenses/LICENSE
youtubevideosorter-1.2.dist-info/METADATA
youtubevideosorter-1.2.dist-info/WHEEL
youtubevideosorter-1.2.dist-info/entry_points.txt
youtubevideosorter-1.2.dist-info/top_level.txt
youtubevideosorter-1.2.dist-info/RECORD
