Metadata-Version: 2.4
Name: youtubevideosorter
Version: 1.2
Summary: Simple tool to sort videos with directories by channel
Author-email: Swee <meow@swee.codes>
License: Unlicense
Project-URL: Repository, https://git.swee.codes/swee/youtubevideosorter
Project-URL: Issues, https://git.swee.codes/swee/youtubevideosorter/issues
Project-URL: Changelog, https://git.swee.codes/swee/youtubevideosorter/releases
Classifier: Programming Language :: Python :: 3
Classifier: Operating System :: OS Independent
Requires-Python: >=3.9
License-File: LICENSE
Requires-Dist: google-api-python-client
Requires-Dist: requests
Requires-Dist: rich
Dynamic: license-file
